{
  "category": "global_environment",
  "last_updated": "2026-05-13T21:15:36.772Z",
  "article_count": 50,
  "articles": [
    {
      "id": "92b3945269711e6f453f4274e94a7de0",
      "title": "Britons urged to place 22p ingredient outside to keep rats and mice away",
      "description": "As spring approaches, it's important to take steps to prevent a rat infestation in your home - and one common kitchen ingredient could help keep them at bay",
      "url": "https://www.express.co.uk/life-style/garden/2204949/rats-mice-22p-ingredient-outside",
      "image_url": "https://cdn.images.express.co.uk/img/dynamic/13/590x/2204949_1.jpg",
      "source_icon": "https://n.bytvi.com/expresscouk.png",
      "source": "Express",
      "published_at": "2026-05-13 09:12:00",
      "language": "english",
      "category": "environment"
    },
    {
      "id": "0a8997ccb13ce757ed7b35e005253aba",
      "title": "Magnus the wandering walrus swaps Scotland for Norway",
      "description": "The young male - who was named Magnus during his travels - is spotted again after crossing the North Sea.",
      "url": "https://www.bbc.com/news/articles/cy82j0q383no",
      "image_url": "https://ichef.bbci.co.uk/news/1024/branded_news/697a/live/98b2da90-4ea3-11f1-92a2-156bc6ac560f.jpg",
      "source_icon": "https://n.bytvi.com/bbc.jpg",
      "source": "The Bbc",
      "published_at": "2026-05-13 09:09:57",
      "language": "english",
      "category": "environment"
    },
    {
      "id": "b968b10ca981a326483e93bac9fc6ec0",
      "title": "Surprise! These 5 Foods Spoil Faster Than You Thought",
      "description": "Olive oil doesn't age like whiskey and brown rice spoils far faster than white. Here are five fridge and pantry staples that don't keep forever.",
      "url": "https://www.cnet.com/how-to/surprise-these-5-foods-spoil-faster-than-you-thought/",
      "image_url": "https://www.cnet.com/a/img/resize/384f58c055759434e7d4503df4a65fa10074a099/hub/2025/07/30/90cdef3f-68ce-4f96-bb26-eb219b78474a/gettyimages-1345381123.jpg?auto=webp&fit=crop&height=614&width=1092",
      "source_icon": "https://n.bytvi.com/cnet.png",
      "source": "Cnet",
      "published_at": "2026-05-13 09:00:40",
      "language": "english",
      "category": "environment"
    },
    {
      "id": "f088eb87883d42d2ec1f34d73a08a6d1",
      "title": "Corpus Christi Faces Water Crisis as Drought and Industrial Growth Strain Supply",
      "description": "Rising demand, municipal dysfunction and drought have pushed Corpus Christi to the edge of a water emergency, offering a cautionary tale for the rest of the country.",
      "url": "https://www.nytimes.com/2026/05/13/us/texas-corpus-christi-water-crisis.html",
      "image_url": "https://static01.nyt.com/images/2026/05/09/multimedia/09nat-corpus-christi-top-option-bmjq/09nat-corpus-christi-top-option-bmjq-mediumSquareAt3X.jpg",
      "source_icon": "https://n.bytvi.com/nytimes.png",
      "source": "The New York Times",
      "published_at": "2026-05-13 09:00:18",
      "language": "english",
      "category": "environment"
    },
    {
      "id": "3458a8f6cb346b648c83868b67fc303a",
      "title": "Why sick pigeons are showing up to this N.S. wildlife rehabilitation centre",
      "description": "Hope for Wildlife says corn that's laced with poison may be the cause. The CBC’s Celina Aalders explains.",
      "url": "https://www.cbc.ca/player/play/9.7197035?cmp=rss",
      "image_url": "https://i.cbc.ca/ais/0f3954bc-93d6-420c-ba27-4ffc3b52fea5,1778616656275/full/max/0/default.jpg?im=Crop%2Crect%3D%280%2C0%2C1280%2C720%29%3B",
      "source_icon": "https://n.bytvi.com/cbc.jpg",
      "source": "Cbc",
      "published_at": "2026-05-13 09:00:00",
      "language": "english",
      "category": "environment"
    },
    {
      "id": "c9313f70b7b7f6808186f6fd98762c7e",
      "title": "Permanent daylight time for P.E.I.? Lantz to talk with Atlantic premiers about it",
      "description": "As some other provinces move toward permanent daylight time, it could spell the end of springing forward and falling back for P.E.I. clocks.",
      "url": "https://www.cbc.ca/news/canada/prince-edward-island/pei-daylight-time-9.7197247?cmp=rss",
      "image_url": "https://i.cbc.ca/ais/3b550717-c2df-4714-b3d9-0b8f15434598,1778621801862/full/max/0/default.jpg?im=Crop%2Crect%3D%280%2C0%2C1920%2C1080%29%3B",
      "source_icon": "https://n.bytvi.com/cbc.jpg",
      "source": "Cbc",
      "published_at": "2026-05-13 09:00:00",
      "language": "english",
      "category": "environment"
    },
    {
      "id": "b4218c681771dfe0f2fbc09b436882cf",
      "title": "Met Office names where Northern Lights will shine Wednesday in Aurora Borealis update",
      "description": "Some lucky Brits may be able to witness the spectacular displays.",
      "url": "https://www.express.co.uk/news/weather/2204921/met-office-northern-lights-uk-wednesday",
      "image_url": "https://cdn.images.express.co.uk/img/dynamic/153/590x/2204921_1.jpg",
      "source_icon": "https://n.bytvi.com/expresscouk.png",
      "source": "Express",
      "published_at": "2026-05-13 08:59:00",
      "language": "english",
      "category": "environment"
    },
    {
      "id": "132744d5a0ce7d44da1814c010dd8022",
      "title": "Toronto's May 13 forecast: Showers",
      "description": null,
      "url": "https://www.thestar.com/news/gta/torontos-may-13-forecast-showers/article_3de67d01-9df6-5027-95c3-c0253d62a8c6.html",
      "image_url": "https://bloximages.chicago2.vip.townnews.com/thestar.com/content/tncms/assets/v3/editorial/f/24/f24b3eb5-a73c-5002-974c-de312dc0cc2d/6827592a30110.image.jpg?crop=1764%2C926%2C0%2C124&resize=1200%2C630&order=crop%2Cresize",
      "source_icon": "https://n.bytvi.com/thestar.png",
      "source": "The Star",
      "published_at": "2026-05-13 08:54:36",
      "language": "english",
      "category": "environment"
    },
    {
      "id": "fe57c7b71bfd2322875732d8305f62cd",
      "title": "Three killed in flooded farm as NSRI rescues 23 trapped on rooftops near Worcester",
      "description": "NSRI crews rescued 23 farm workers and their families trapped on rooftops between Worcester and Rawsonville after severe flooding, while three people were recovered dead from a flooded Western Cape farm.",
      "url": "https://www.iol.co.za/news/south-africa/three-killed-in-flooded-farm-as-nsri-rescues-23-trapped-on-rooftops-near-worcester-0e49a1de-4150-4b35-a2bb-4f5e7f8e3fb0",
      "image_url": "https://image-prod.iol.co.za/16x9/800?source=https://iol-prod.appspot.com/image/fe13f463818f0d961ada1b3003bfb83d01b6ec40/3641&operation=CROP&offset=0x305&resize=3641x2048",
      "source_icon": "https://n.bytvi.com/iol.png",
      "source": "Iol",
      "published_at": "2026-05-13 08:51:35",
      "language": "english",
      "category": "environment"
    },
    {
      "id": "547c0b1a88ad2d38561b3c6c7847b497",
      "title": "Temperatures drop to unseasonably low levels as cold snap grips UK",
      "description": null,
      "url": "https://www.independent.co.uk/bulletin/news/met-office-weather-uk-cold-arctic-b2975599.html",
      "image_url": "https://static.independent.co.uk/2025/04/15/13/04/Spring-weather-April-15th-2025-lonwli1n.jpeg?width=1200&auto=webp&trim=0%2C0%2C0%2C0",
      "source_icon": "https://n.bytvi.com/independentuk.png",
      "source": "The Independent",
      "published_at": "2026-05-13 08:48:44",
      "language": "english",
      "category": "environment"
    },
    {
      "id": "ac53fbbeb8f886aaa35991a9e56cd043",
      "title": "River upgrading works linked to Jalan 223 flash floods, says PJ mayor",
      "description": "PETALING JAYA: Ongoing river upgrading works at Sungai Penchala contributed to the recent flash floods near Jalan 223.",
      "url": "https://www.thestar.com.my/metro/metro-news/2026/05/13/river-upgrading-works-linked-to-jalan-223-flash-floods-says-pj-mayor",
      "image_url": "https://apicms.thestar.com.my/uploads/images/2026/05/13/3905680.jpg",
      "source_icon": "https://n.bytvi.com/thestar_my.png",
      "source": "The Star",
      "published_at": "2026-05-13 05:52:00",
      "language": "english",
      "category": "environment"
    },
    {
      "id": "85f4d3d913ce2131d4af525bb605cbc8",
      "title": "UK weather maps turn orange for 27C scorcher - with 16 regions hotter than Greece",
      "description": "The UK is set for a scorcher with temperatures in the 20s across the nation and highs of 27C",
      "url": "https://www.express.co.uk/news/weather/2204879/uk-weather-maps-turn-orange",
      "image_url": "https://cdn.images.express.co.uk/img/dynamic/153/590x/2204879_1.jpg",
      "source_icon": "https://n.bytvi.com/expresscouk.png",
      "source": "Express",
      "published_at": "2026-05-13 05:48:00",
      "language": "english",
      "category": "environment"
    },
    {
      "id": "4ff34a4a5bbd34d5ba98959e5f335794",
      "title": "Scientists discover a mysterious silicone pollutant that may be everywhere",
      "description": "Researchers have uncovered unexpectedly high levels of silicone-based pollutants called methylsiloxanes floating through the atmosphere across cities, rural regions, and even forests. Much of the pollution appears to come from vehicle emissions, likely linked to engine oil additives that survive combustion and escape into the air. Scientists say humans may inhale more of these compounds daily than other notorious pollutants like PFAS or microplastics.",
      "url": "https://www.sciencedaily.com/releases/2026/05/260512202353.htm",
      "image_url": "https://www.sciencedaily.com/images/1920/man-coughing-outside-building.webp",
      "source_icon": "https://n.bytvi.com/sciencedaily.png",
      "source": "Science Daily",
      "published_at": "2026-05-13 05:47:53",
      "language": "english",
      "category": "breaking"
    },
    {
      "id": "314dabed95c6e1a24d8d8c090006ee1b",
      "title": "A moment that changed me: I saw my first total solar eclipse – and its beauty shook me to my core",
      "description": "As an astronomer, I had witnessed many celestial phenomena. But nothing prepared me for those few minutes in 2017 when the world fell silent I have never driven with more determination than when rushing away from Shelby Park in Nashville. We had reached Davidson Street when my husband shouted: “There! There’s sunlight!” I skidded into a car park of a printing company with barely any time to spare. We jumped out of the car, put on our dark glasses, and looked at the quickly disappearing sun. It was surrounded by clouds, but a tiny sliver of light was still shining. This was 1.27pm on 21 August 2017. We had travelled all the way from London to Tennessee to experience the Great American Eclipse – an astronomical phenomenon I had never seen before. As an Italian-born astronomer, I had always felt at a bit of a disadvantage. I have a doctorate in astrophysics, focused on collisions between galaxies. I have seen many celestial phenomena – comets, planetary alignments, fireballs, galaxies, northern lights – but not a total solar eclipse. Continue reading...",
      "url": "https://www.theguardian.com/lifeandstyle/2026/may/13/a-moment-that-changed-me-i-saw-my-first-total-solar-eclipse-and-its-beauty-shook-me-to-my-core",
      "image_url": "https://i.guim.co.uk/img/media/e8f4824f417bdf0763b78ffdef6a1c27bdba0091/73_0_1923_1538/master/1923.jpg?width=140&quality=85&auto=format&fit=max&s=26a4d526e67e1dab4e26e8689005cc7e",
      "source_icon": "https://n.bytvi.com/theguardiantheguardian.png",
      "source": "Theguardiantheguardian",
      "published_at": "2026-05-13 05:45:20",
      "language": "english",
      "category": "environment"
    },
    {
      "id": "6848f6da98c4c6993e96c6ccd3a6353e",
      "title": "Smoking and vaping may be banned in list of outdoor places",
      "description": "The Government is planing to extend the current rules to make smoking even tougher",
      "url": "https://www.mirror.co.uk/news/health/smoking-vaping-banned-list-outdoor-37147908",
      "image_url": "https://i2-prod.mirror.co.uk/incoming/article37147913.ece/ALTERNATES/s615/0_GettyImages-679008936-1.jpg",
      "source_icon": "https://n.bytvi.com/mirroruk.png",
      "source": "Mirror",
      "published_at": "2026-05-13 05:38:31",
      "language": "english",
      "category": "environment"
    },
    {
      "id": "5077ca399ca5a5fb7b623cfbb383638a",
      "title": "Acciona expands rural electricity service in PH to 21,400 people",
      "description": "Acciona.org extended its “Luz enCasa” renewable electricity supply program to almost 21,400 people (+80%) in the Philippines in 2025, after expanding its activity to the province of Pampanga. The non-profit organization brought its service, based on photovoltaic systems and batteries, to 4,435 homes, as well as small businesses, educational centers, and community centers, scattered across 103 communities in Palawan and Pampanga where such service is not guaranteed by the conventional electricity grid. Across the Philippes, acciona.org’s impact in 2025 resulted in a significant improvement in living conditions, including: 1) Poverty reduction. 4,435 households benefited from savings on their energy expenses [...]... Keep on reading: Acciona expands rural electricity service in PH to 21,400 people",
      "url": "https://pep.inquirer.net/3122/acciona-expands-rural-electricity-service-in-ph-to-21400-people",
      "image_url": "https://pep.inquirer.net/files/2026/05/microsoftteams-image-5-300x150.jpg",
      "source_icon": "https://n.bytvi.com/inquirer.png",
      "source": "Inquirer",
      "published_at": "2026-05-13 05:31:06",
      "language": "english",
      "category": "top"
    },
    {
      "id": "70abd4b9557d22e70894c6d17ca6b0ed",
      "title": "Cacti are evolving shockingly fast and scientists just learned why",
      "description": "Cacti may look like slow, stubborn desert survivors, but they’re actually evolving at lightning speed. Scientists studying more than 750 cactus species discovered that what really drives the explosion of new cactus species isn’t flower size or specialized pollinators, but how quickly cactus flowers change shape over time. The finding overturns a long-standing idea dating back to Darwin and reveals deserts as surprisingly dynamic ecosystems where evolution is happening fast.",
      "url": "https://www.sciencedaily.com/releases/2026/05/260512202347.htm",
      "image_url": "https://www.sciencedaily.com/images/1920/multicolored-cactus.webp",
      "source_icon": "https://n.bytvi.com/sciencedaily.png",
      "source": "Science Daily",
      "published_at": "2026-05-13 05:30:11",
      "language": "english",
      "category": "environment"
    },
    {
      "id": "8bf5f602b0183da6adbda5345981c505",
      "title": "Fears for green belt as homes application lodged for more than 500 homes in Kingswinford",
      "description": "Campaigners hit out after another application means a West Midlands village could see more than 1,700 new homes",
      "url": "https://www.birminghammail.co.uk/black-country/fears-green-belt-homes-application-33933742",
      "image_url": "https://i2-prod.birminghammail.co.uk/black-country/article33933741.ece/ALTERNATES/s615/0_The-Kingswinford-Triangle.jpg",
      "source_icon": "https://n.bytvi.com/birminghammail.png",
      "source": "Birmingham Live",
      "published_at": "2026-05-13 05:30:00",
      "language": "english",
      "category": "environment"
    },
    {
      "id": "5e639d791df1e676f3cc7cfed8d2a5bc",
      "title": "Fruit and vegetables are toxic to my child",
      "description": "There are calls for newborn babies to be routinely screened for Hereditary Fructose Intolerance.",
      "url": "https://www.bbc.com/news/articles/cy82d6l7vlgo",
      "image_url": "https://ichef.bbci.co.uk/news/1024/branded_news/ba88/live/8cbcb9a0-4d35-11f1-87e0-250b0c741d1e.jpg",
      "source_icon": "https://n.bytvi.com/bbc.jpg",
      "source": "The Bbc",
      "published_at": "2026-05-13 05:29:25",
      "language": "english",
      "category": "environment"
    },
    {
      "id": "cf2fef0fb7192df1699c2dbe8bf9d0c2",
      "title": "Marble-sized hail expected with thunderstorms to hit 5 Michigan counties Wednesday – gusts up to 40 mph",
      "description": "A weather alert was issued by the National Weather Service on Wednesday at 1:20 a.m. EDT for strong thunderstorms until 2:15 a.m. EDT for Shiawassee, Genesee, Lapeer, Livingston and Oakland counties.",
      "url": "https://www.mlive.com/weather-alerts/2026/05/marble-sized-hail-expected-with-thunderstorms-to-hit-5-michigan-counties-wednesday-gusts-up-to-40-mp.html",
      "image_url": "https://www.mlive.com/resizer/v2/QVSRZ3J3A5ADRB3NGUNCM2ODXQ.png?auth=9ca833dde5c0145ced4b1ad9289bede5404fec95a235b58f5710d798ab1c08f5&smart=true&height=1200",
      "source_icon": "https://n.bytvi.com/mlive.png",
      "source": "Mlive",
      "published_at": "2026-05-13 05:25:25",
      "language": "english",
      "category": "environment"
    },
    {
      "id": "3fffcd3292f8f4f224d9f79537c3a6c3",
      "title": "Smuggled in syringes: how Nairobi became a nexus for the black market in giant harvester ants",
      "description": "Court cases in Kenya point to a growing market for ants as exotic pets in Asia and Europe that has implications for conservation and biosecurity In the biblical text Book of Proverbs, King Solomon describes the harvester ant as a model of wisdom and industriousness: “Go to the ant, you sluggard; consider its ways and be wise!” Almost 3,000 years later, the thriving international parallel market for a distinct species of the ant native to east Africa has been thrust into the global spotlight after a series of convictions in Kenya for ant smuggling. Continue reading...",
      "url": "https://www.theguardian.com/environment/ng-interactive/2026/may/13/smuggled-illegal-global-trade-giant-harvester-ants-kenya-asia-europe",
      "image_url": "https://i.guim.co.uk/img/media/88f7fb875f287b024c2a91f828e752e77950744c/617_0_3500_2800/master/3500.jpg?width=140&quality=85&auto=format&fit=max&s=7a0bd3b3f807c211ebaf6ac3cd407446",
      "source_icon": "https://n.bytvi.com/theguardiantheguardian.png",
      "source": "Theguardiantheguardian",
      "published_at": "2026-05-13 02:00:16",
      "language": "english",
      "category": "environment"
    },
    {
      "id": "d01b3fd600e50d04018fa60ece33976b",
      "title": "Hydrangeas will flower more in hot sunny weather if watered with 1 natural item in May",
      "description": "Hydrangeas have a bad habit of wilting or not flowering at all if not cared for properly in late spring, but there is a natural way to help them bloom without spending any money at all.",
      "url": "https://www.express.co.uk/life-style/garden/2204755/how-to-help-hydrangeas-bloom-in-may",
      "image_url": "https://cdn.images.express.co.uk/img/dynamic/13/590x/2204755_1.jpg",
      "source_icon": "https://n.bytvi.com/expresscouk.png",
      "source": "Express",
      "published_at": "2026-05-13 02:00:00",
      "language": "english",
      "category": "environment"
    },
    {
      "id": "f0213818ee982e326556fa828271a706",
      "title": "Jim Chalmers’ budget doesn’t fix everything – but it’s an overdue first payment to future generations | Ken Henry",
      "description": "The treasurer has shown economic reforms should not be left to the too-hard basket, and instead be pursued with a sense of urgency Explore all of our 2026 Australia federal budget coverage Follow our Australia news live blog for latest updates Get our breaking news email , free app or daily news podcast Finally, a budget of economic reform. It has been too long coming. At this stage of the economic cycle, the budget should be in surplus. It should not be adding tens of billions of dollars every year to the mountain of public debt. Sixteen years after the release of the tax review commissioned by the Rudd government, our tax system should be supporting much better budget outcomes. It should be underwriting much stronger productivity growth. It should be delivering a much better deal for young Australian workers. And it should be delivering to Australians a much bigger share of the resource rents being extracted by the foreign multinationals exploiting our finite natural resources. So, this budget doesn’t fix everything. Continue reading...",
      "url": "https://www.theguardian.com/australia-news/commentisfree/2026/may/13/australia-budget-2026-jim-chalmers-economic-reforms-tax-changes-future-generations",
      "image_url": "https://i.guim.co.uk/img/media/e566c42ee2e9e3c28912ed56d8192a2e3db560be/2654_323_5471_4377/master/5471.jpg?width=140&quality=85&auto=format&fit=max&s=b30b4dda029f708fb2087222fb99ea03",
      "source_icon": "https://n.bytvi.com/theguardian.jpg",
      "source": "The Guardian",
      "published_at": "2026-05-13 01:57:41",
      "language": "english",
      "category": "environment"
    },
    {
      "id": "d228bc3cf1afe77bb1c372c65a95d604",
      "title": "Toilets will stay clean without any staining if you swap bleach for 1 natural 'magic' item",
      "description": "Toilets often become stained as a lot of households do not know how to clean them properly, and it is actually better to swap out bleach for a cheaper yet highly effective item.",
      "url": "https://www.express.co.uk/life-style/property/2204326/how-to-clean-toilets-properly-without-bleach",
      "image_url": "https://cdn.images.express.co.uk/img/dynamic/51/590x/2204326_1.jpg",
      "source_icon": "https://n.bytvi.com/expresscouk.png",
      "source": "Express",
      "published_at": "2026-05-13 01:48:00",
      "language": "english",
      "category": "environment"
    },
    {
      "id": "d826448fc5c21d5cc6a4968b81eaabc6",
      "title": "A rare cancer-fighting plant compound has been decoded",
      "description": "Scientists at UBC Okanagan have uncovered how plants produce mitraphylline, a rare natural compound with promising anti cancer potential. The team identified two enzymes that work together to build the molecule’s unusual twisted structure, solving a mystery that had puzzled researchers for years. Because mitraphylline appears only in tiny amounts in tropical plants like kratom and cat’s claw, the discovery could make it far easier to produce sustainably in the future.",
      "url": "https://www.sciencedaily.com/releases/2026/05/260512213836.htm",
      "image_url": "https://www.sciencedaily.com/images/1920/cancer-cell-self-destructing.webp",
      "source_icon": "https://n.bytvi.com/sciencedaily.png",
      "source": "Science Daily",
      "published_at": "2026-05-13 01:45:40",
      "language": "english",
      "category": "environment"
    },
    {
      "id": "72139d4a5c56983241a03293a4faea57",
      "title": "New Director Representing the City of Los Angeles Joins Metropolitan Board of Directors",
      "description": "LOS ANGELES--(BUSINESS WIRE)--Sustainable food and water policy leader Paula Daniels was seated Tuesday as the City of Los Angeles’ newest representative on the board of directors of the Metropolitan Water District of Southern California. Daniels has spent more than two decades working to advance public policy on food systems and sustainability in the government, academic and non-profit sectors. She is currently the inaugural executive director of the Los Angeles County Office of Food Systems,",
      "url": "http://www.businesswire.com/news/home/20260512121589/en/New-Director-Representing-the-City-of-Los-Angeles-Joins-Metropolitan-Board-of-Directors/?feedref=JjAwJuNHiystnCoBq_hl-ZzpnHS32O5tBfLZHwy8L1lVsKLHj4l7ufu4XoarznHcCc3RCn2ioKmwBZbtUT_laxlCBS-6lALTzeuzMorsqlUBRXBIbEfS-L7bFkq7lPbqxuv9GxLR3d-mCpNfrf5FyQ%3D%3D",
      "image_url": "https://mms.businesswire.com/media/20260512121589/en/1110664/22/MWD_Seal_1_inch.jpg",
      "source_icon": "https://n.bytvi.com/businesswire.png",
      "source": "Businesswire",
      "published_at": "2026-05-13 01:44:00",
      "language": "english",
      "category": "environment"
    },
    {
      "id": "e2d357689805b9156508e23fa440b313",
      "title": "Gardeners urged to spray natural solution in gardens to keep foxes and cats away",
      "description": "Cats and foxes can be a huge problem for gardeners in spring, but this cheap homemade herb deterrent could help keep them out of your garden naturally",
      "url": "https://www.express.co.uk/life-style/garden/2204674/how-to-deter-cats-foxes-from-gardens",
      "image_url": "https://cdn.images.express.co.uk/img/dynamic/13/590x/2204674_1.jpg",
      "source_icon": "https://n.bytvi.com/expresscouk.png",
      "source": "Express",
      "published_at": "2026-05-13 01:27:00",
      "language": "english",
      "category": "environment"
    },
    {
      "id": "86de53b69e6fc28c88de4223635e642a",
      "title": "Midwest Food Bank volunteers prepare supplies for Arizona heat relief centers ahead of brutal summer",
      "description": "Volunteers at Midwest Food Bank in Gilbert packed food and supplies bound for heat relief and respite centers across Arizona as triple-digit temperatures return to the Valley.",
      "url": "https://www.abc15.com/news/region-southeast-valley/gilbert/midwest-food-bank-volunteers-prepare-supplies-for-arizona-heat-relief-centers-ahead-of-brutal-summer",
      "image_url": "https://ewscripps.brightspotcdn.com/dims4/default/3c40b58/2147483647/strip/true/crop/1280x672+0+24/resize/1200x630!/quality/90/?url=https%3A%2F%2Fcf.cdn.uplynk.com%2Fause1%2Fslices%2F2cd%2F5c3d34b8b29a45469a86c02775b7a2cf%2F2cd434bbf02741c5b5d7df6bda1bfe3f%2Fposter_8bf246cd1e33434c82c92f4325d2a0bd.jpg",
      "source_icon": "https://n.bytvi.com/abc15.png",
      "source": "Abc 15",
      "published_at": "2026-05-13 01:25:25",
      "language": "english",
      "category": "environment"
    },
    {
      "id": "c338dcef5679fa2d93108135d5c80fb4",
      "title": "4.0 magnitude earthquake rattles Haida Gwaii residents",
      "description": "The quake hit about 31 kilometres from the village of Daajing Giids around 1:30 p.m. PT Tuesday. No damage was reported.",
      "url": "https://www.cbc.ca/news/canada/british-columbia/haida-gwaii-earthquake-9.7197533?cmp=rss",
      "image_url": "https://i.cbc.ca/ais/59031ea7-082d-4574-a670-3f6009c4299c,1735684063915/full/max/0/default.jpg?im=Crop%2Crect%3D%280%2C0%2C1920%2C1080%29%3B",
      "source_icon": "https://n.bytvi.com/cbc.jpg",
      "source": "Cbc",
      "published_at": "2026-05-13 01:17:45",
      "language": "english",
      "category": "environment"
    },
    {
      "id": "af81c7777b347706f1232bc940c0bf44",
      "title": "Solar eclipse to attract thousands to 'middle of nowhere' in 2028",
      "description": "One of the longest solar eclipses this century, albeit for five minutes, is set to put the remote East Kimberley on the world map.",
      "url": "https://www.abc.net.au/news/2026-05-13/five-minute-solar-eclipse-wa-north-kimberley/106670658",
      "image_url": "https://live-production.wcms.abc-cdn.net.au/29d417d52cccb661b67cc9f6d63b9d9c?impolicy=wcms_crop_resize&cropH=2562&cropW=4554&xPos=0&yPos=237&width=862&height=485",
      "source_icon": "https://n.bytvi.com/abc_net.png",
      "source": "Abc",
      "published_at": "2026-05-13 01:07:47",
      "language": "english",
      "category": "environment"
    },
    {
      "id": "f7f7a82b089b9538b393e982d3d00f04",
      "title": "Scientists solve Bermuda mystery after discovering hidden structure below the Atlantic waters",
      "description": "A massive hidden structure the size of New York has been uncovered sitting beneath Bermuda and scientists have never discovered a formation like it.",
      "url": "https://www.dailymail.com/sciencetech/article-15812311/bermuda-hidden-rock-atlantic-scientists.html",
      "image_url": "https://i.dailymail.com/1s/2026/05/12/22/108563261-0-image-a-19_1778623173134.jpg",
      "source_icon": "https://n.bytvi.com/dailymailuk.png",
      "source": "Mail Online",
      "published_at": "2026-05-12 22:09:41",
      "language": "english",
      "category": "environment"
    },
    {
      "id": "931848f037cfdb4e7a6d1e69eb224591",
      "title": "World's Oldest Oak Is Spared From Developers' Bulldozers In Riverside County",
      "description": "The plant is believed to be at least 13,000 years old. An agreement was reached Tuesday to save it.",
      "url": "https://patch.com/california/lakeelsinore-wildomar/worlds-oldest-oak-located-riverside-county-its-been-spared",
      "image_url": "https://patch.com/img/cdn20/users/98363/20260512/060649/styles/patch_image/public/rsjurupa-oak-aaron-echols-fpwc-dg1max-800x800___12180204805.jpg",
      "source_icon": "https://n.bytvi.com/patch.png",
      "source": "Patch",
      "published_at": "2026-05-12 22:06:50",
      "language": "english",
      "category": "environment"
    },
    {
      "id": "2d632acee40497644b2820b97f0cdaa6",
      "title": "5/12/26: Clear Skies and 76 High, 61 Low; Light Winds, No Precipitation, Pleasant Evening Conditions",
      "description": "At 5:05 PM, Williamson County reports a current temperature of 75.9°F with a light wind from the south at 6 mph. There has been no precipitation recorded today, and the skies are clear. Earlier today, the temperature reached a high of 76.3°F, with a low of 45.1°F. Winds were calm, reaching up to 6.1 mph [...] The post 5/12/26: Clear Skies and 76 High, 61 Low; Light Winds, No Precipitation, Pleasant Evening Conditions appeared first on Williamson Source .",
      "url": "https://williamsonsource.com/5-12-26-clear-skies-and-76-high-61-low-light-winds-no-precipitation-pleasant-evening-conditions/",
      "image_url": "https://williamsonsource.com/wp-content/uploads/2025/08/clearday2.jpg",
      "source_icon": "https://n.bytvi.com/williamsonsource.png",
      "source": "Williamson Source",
      "published_at": "2026-05-12 22:05:14",
      "language": "english",
      "category": "environment"
    },
    {
      "id": "c82fbd8d70a2fd1a7793fa5f8e06e123",
      "title": "Witness describes scene after man wildly shoots a rifle at drivers near Boston",
      "description": "A witness whose apartment overlooks the scene initially thought he was hearing construction equipment when the banging noises started.",
      "url": "https://apnews.com/video/witness-describes-scene-after-man-wildly-shoots-a-rifle-at-drivers-near-boston-c6dd93d373ec4989b3183731fa81662e",
      "image_url": "https://dims.apnews.com/dims4/default/7422896/2147483647/strip/false/crop/1920x1080+0+0/resize/980x551!/quality/90/?url=https%3A%2F%2Fassets.apnews.com%2F50%2Fa3%2F2a912f00765fde400348aeee79f0%2Fus-ma-cambridge-shooting-reax-20260512cr-1920x1080.jpg",
      "source_icon": "https://n.bytvi.com/apnews.png",
      "source": "Apnews",
      "published_at": "2026-05-12 22:04:39",
      "language": "english",
      "category": "environment"
    },
    {
      "id": "beab3229d82cf8ee8b57768d06f37b77",
      "title": "Councillors wanting federal government to up the ante for sewage treatment plant",
      "description": "Some Winnipeg councillors are looking to get the federal government to commit more to the next phase of the sewage treatment plant, saving Winnipeggers money.",
      "url": "https://www.ctvnews.ca/winnipeg/article/councillors-wanting-federal-government-to-up-the-ante-for-sewage-treatment-plant/",
      "image_url": "https://www.ctvnews.ca/resizer/v2/KTFXWB3VVIWIJIAJSGDKQPQEKU.png?auth=19a751d5ad9566c272d20e8c752a79124638eee76286be2a45d6867b8a418467&smart=true&width=1020&height=574",
      "source_icon": "https://n.bytvi.com/ctvnews.png",
      "source": "Ctv News",
      "published_at": "2026-05-12 22:04:03",
      "language": "english",
      "category": "environment"
    },
    {
      "id": "1578586f1bba3b6f53cace73edf6677a",
      "title": "'Hidden Gem' Woodland Area Of Camden County To Be Officially Preserved",
      "description": "The area has both ecological and historical significance.",
      "url": "https://patch.com/new-jersey/cherryhill/hidden-gem-woodland-area-camden-county-be-officially-preserved",
      "image_url": "https://patch.com/img/cdn20/users/27133192/20260512/055625/styles/patch_image/public/dsc09188___12175529728.jpg",
      "source_icon": "https://n.bytvi.com/patch.png",
      "source": "Patch",
      "published_at": "2026-05-12 22:03:46",
      "language": "english",
      "category": "environment"
    },
    {
      "id": "26c8c50648395bee464f0838cb26d1fe",
      "title": "U.S. Plastics Pact Releases New Strategies to Enable Composting at Scale",
      "description": "WALPOLE, N.H.--(BUSINESS WIRE)--The U.S. Plastics Pact (USPP) today released a new resource outlining how well-designed policies can accelerate composting infrastructure, support compostable packaging systems, and divert food waste and food-contaminated materials from landfills. Enabling Composting at Scale highlights the sustained investment, supportive policy frameworks, and coordinated system design needed to advance a circular economy for food and packaging in the United States. A significa",
      "url": "http://www.businesswire.com/news/home/20260512456758/en/U.S.-Plastics-Pact-Releases-New-Strategies-to-Enable-Composting-at-Scale/?feedref=JjAwJuNHiystnCoBq_hl-X2BgZ-vGn4dO0OtHrHlsBouWxj09bKgFPs8Ri9iZvJhWJT50v2g3Ei-19qH0fyPszGrim8IhAkVNXbaI1AGppOzkqEXpa07kut2m9xviGvGbQQtmzdfgYBqoK3SS-VE4Q%3D%3D",
      "image_url": "https://mms.businesswire.com/media/20260512456758/en/2803666/22/USPP_Logo.jpg",
      "source_icon": "https://n.bytvi.com/businesswire.png",
      "source": "Businesswire",
      "published_at": "2026-05-12 21:53:00",
      "language": "english",
      "category": "environment"
    },
    {
      "id": "61aaf6550bfbd08cfb7fb7527461c841",
      "title": "Up to 25 mm of rain possible in the Toronto area overnight: conservation authority",
      "description": "A storm is expected to bring up to 25 millimetres of rain to the Toronto area Tuesday night and into Wednesday morning, according to the Toronto and Region Conservation Authority (TRCA).",
      "url": "https://www.ctvnews.ca/toronto/local/article/up-to-25-mm-of-rain-possible-in-the-toronto-area-overnight-conservation-authority/",
      "image_url": "https://www.ctvnews.ca/resizer/v2/P4NV545ARQCRXT6QRBWE7QZKOM.jpg?auth=40856cc572ff4832d6714ed61c0f4744a67767260cb41486c9902d3c280d7544&smart=true&width=1020&height=574",
      "source_icon": "https://n.bytvi.com/ctvnews.png",
      "source": "Ctv News",
      "published_at": "2026-05-12 21:44:11",
      "language": "english",
      "category": "environment"
    },
    {
      "id": "7531710b0c7b173aca858ee32cbd97e9",
      "title": "Ombudsman Remulla gets Senate flood report",
      "description": "MANILA, Philippines — The Office of the Ombudsman on Tuesday said it has received the Senate blue ribbon committee report on its partial findings on the flood control scam, which includes a recommendation that some lawmakers undergo preliminary investigation for the possible filing of charges. “I am confirming receipt of the transmittal of the partial [...]... Keep on reading: Ombudsman Remulla gets Senate flood report",
      "url": "https://newsinfo.inquirer.net/2227662/ombudsman-remulla-gets-senate-flood-report",
      "image_url": "https://newsinfo.inquirer.net/files/2026/04/1209120-e1776786657454-620x372.jpeg",
      "source_icon": "https://n.bytvi.com/inquirer.png",
      "source": "Inquirer",
      "published_at": "2026-05-12 21:44:00",
      "language": "english",
      "category": "environment"
    },
    {
      "id": "33b5f4c0ec166ec9b9029f2173d01324",
      "title": "Cinco the jaguar spotted in Arizona's Sky Islands. See the video",
      "description": "Cinco, the endangered jaguar, is still roaming Arizona's Sky Islands, and the proof is on a trail video camera.",
      "url": "https://www.azcentral.com/story/news/local/arizona-environment/2026/05/12/endangered-jaguar-cinco-spotted-in-arizona-sky-islands/90049349007/",
      "image_url": "https://www.azcentral.com/gcdn/authoring/authoring-images/2026/05/12/PPHX/90050760007-20260327192722.JPG?crop=1499,843,x0,y17&width=1499&height=749&format=pjpg&auto=webp",
      "source_icon": "https://n.bytvi.com/azcentral.png",
      "source": "The Arizona Republic",
      "published_at": "2026-05-12 21:38:31",
      "language": "english",
      "category": "environment"
    },
    {
      "id": "95b6e91f1dfb5e02c5992a616350b11c",
      "title": "WHO warns that more hantavirus cases are likely — but ‘no sign’ of widespread outbreak from cruise ship",
      "description": "The World Health Organization announced it expects more cases of hantavirus to crop up in the days and weeks ahead, but assured there are no indications of a wider outbreak on the horizon.",
      "url": "https://nypost.com/2026/05/12/world-news/who-says-more-hantavirus-cases-likely-but-no-sign-of-widespread-outbreak/",
      "image_url": "https://nypost.com/wp-content%2Fuploads%2Fsites%2F2%2F2026%2F05%2Fpassengers-disembarked-hantavirus-stricken-127555584.jpg?quality%3D90%26strip%3Dall",
      "source_icon": "https://n.bytvi.com/nypost.png",
      "source": "New York Post",
      "published_at": "2026-05-12 18:39:39",
      "language": "english",
      "category": "environment"
    },
    {
      "id": "87049801ca5e910eb03c8d72a137451e",
      "title": "L.A. quietly fires its first chief heat officer",
      "description": "Marta Segura stepped into the new role in 2022 amid a dramatic increase in climate-fueled heat events.",
      "url": "https://www.latimes.com/environment/story/2026-05-12/la-parts-ways-with-its-first-chief-heat-officer",
      "image_url": "https://ca-times.brightspotcdn.com/dims4/default/a16ec8f/2147483647/strip/false/crop/7363x4956+0+0/resize/1486x1000!/quality/75/?url=https%3A%2F%2Fcalifornia-times-brightspot.s3.amazonaws.com%2F16%2F00%2Fb015ec2840a2981bea30f0f53150%2F1373823-la-power-list-marta-segura-cmh-02.jpg",
      "source_icon": "https://n.bytvi.com/latimes.png",
      "source": "Los Angeles Times",
      "published_at": "2026-05-12 18:38:26",
      "language": "english",
      "category": "environment"
    },
    {
      "id": "bdbfb7f87238e7893c0fbfa4a9d4af40",
      "title": "The humanitarian situation in Colombia has reached its worst level in a decade, says the International Commit",
      "description": "The impact of armed conflict on civilians in Colombia over the past year has been the worst in a decade as the country's security situation deteriorates, the International Committee of the Red Cross said Tuesday in an annual report.",
      "url": "https://apnews.com/video/the-humanitarian-situation-in-colombia-has-reached-its-worst-level-in-a-decade-says-the-international-committee-of-the-red-cross-8241154fa07f45b18ca9c6e49883951c",
      "image_url": "https://dims.apnews.com/dims4/default/807eef7/2147483647/strip/false/crop/1920x1080+0+0/resize/980x551!/quality/90/?url=https%3A%2F%2Fassets.apnews.com%2Fd9%2F06%2Fba902f04641a853f746444c0bcca%2Fcol-humanitarian-crisis-report-20260512cr-1920x1080.jpg",
      "source_icon": "https://n.bytvi.com/apnews.png",
      "source": "Apnews",
      "published_at": "2026-05-12 18:36:30",
      "language": "english",
      "category": "environment"
    },
    {
      "id": "07a221899f344acb2897209f5280aeee",
      "title": "See map of wildfires burning in Florida",
      "description": "Map shows where wildfires are burning in Florida as containment efforts continue.",
      "url": "https://www.usatoday.com/story/news/nation/2026/05/12/florida-wildfires-map/90044361007/",
      "image_url": "https://www.usatoday.com/gcdn/authoring/authoring-images/2026/05/12/USAT/90047271007-20260512-t-065612-z-1855922243-rc-2-g-7-lajcit-6-rtrmadp-3-usawildfire.JPG?crop=2559,1439,x0,y0&width=1600&height=800&format=pjpg&auto=webp",
      "source_icon": "https://n.bytvi.com/usatoday.jpg",
      "source": "Usa Today",
      "published_at": "2026-05-12 18:36:14",
      "language": "english",
      "category": "environment"
    },
    {
      "id": "80ce74e9f8c62d17a86695d5fc2a6b56",
      "title": "Cannes jury arrive for opening ceremony",
      "description": "Demi Moore, Stellan Skarsgård and Chloé Zhao arrive with jury head Park Chan-wook at the Cannes Film Festival, which is kicking off on the French Riviera. (May 12)",
      "url": "https://apnews.com/video/cannes-jury-arrive-for-opening-ceremony-454a66aaec654a418ef9fcc71290b910",
      "image_url": "https://dims.apnews.com/dims4/default/e95c1a3/2147483647/strip/false/crop/1280x720+0+0/resize/980x551!/quality/90/?url=https%3A%2F%2Fassets.apnews.com%2F4a%2Fc1%2F4d8f881fda809979ac348f691c76%2Ffra-sr-cannes-jury-arrival-20260512e-autocr-1920x1080.jpg",
      "source_icon": "https://n.bytvi.com/apnews.png",
      "source": "Apnews",
      "published_at": "2026-05-12 18:35:37",
      "language": "english",
      "category": "environment"
    },
    {
      "id": "9595e3512632954addc3afbf3a3ecfdf",
      "title": "A study just found brain-eating amoeba in 2 popular U.S. national parks. Here’s what you need to know",
      "description": "Yes, you read that right: Brain-eating amoeba have been found in two popular U.S. national parks, according to a recent study from the U.S. Geological Survey, and a number of other institutions, published in the American Chemical Society’s journal, ES&T Water . Here’s what to know. What happened? Researchers took 185 water samples from five popular U.S. national parks, looking at “40 thermally impacted recreational waters” at Yellowstone National Park, Grand Teton National Park, Lake Mead National Recreation Area, Olympic National Park, and Newberry National Volcanic Monument over an eight year period from 2016 to 2024. What they found revealed widespread detection of Naegleria fowleri (dubbed “brain-eating amoeba”) in 34% of the samples, or 63 specimens, at Yellowstone, Lake Mead, and Grand Teton hot springs and thermally impacted waters. However, the brain-eating amoeba was not found at Olympic National Park or Newberry National Volcanic Monument. It’s important to note that no infections or deaths due to the brain-eating amoeba have been reported at the detection sites. What is Naegleria fowleri ? Naegleria fowleri is a free-living amoeba, a one-celled organism that thrives in warm freshwater lakes, rivers, and hot springs. It’s called the “brain-eating amoeba” because it can infect and destroy brain tissue, according to the Centers for Disease Control and Prevention (CDC) . While brain infections caused by Naegleria fowleri are quite rare, they are nearly always fatal, at a rate of 98%. If water containing the amoeba goes up a person’s nose into the brain, it can cause an infection called primary amebic meningoencephalitis, or PAM. Typically, fewer than 10 people a year in the U.S. get PAM. However, almost everyone who gets PAM dies from it, per the CDC: Out of 167 reported cases of PAM in the U.S. between 1962 to 2024, only four people survived. Exposure risks Brain infections caused by Naegleria fowleri usually occur after a person goes swimming or diving in a lake, river, or other fresh water in the summer after a prolonged period when it was hot, causing higher water temperatures but lower water levels. The CDC cautions you cannot contract the Naegleria fowleri infection simply by swallowing water containing the amoeba, nor can a person pass it to another person. How to reduce the risk of contracting a Naegleria fowleri infection The CDC suggests people hold their nose or wear a nose clip if they are jumping or diving into fresh water , and to keep their head above water in hot springs. Don’t dig in shallow water, because Naegleria fowleri is more likely to live there. Signs and symptoms of a Naegleria fowleri infection Primary amebic meningoencephalitis (PAM) progresses quickly, with early symptoms that can include headache, fever, nausea and vomiting , stiff neck, confusion, lack of attention to people and surroundings, loss of balance, and hallucinations. Most people with PAM die within 18 days after experiencing initial symptoms, with many entering a coma and dying after 5 days, per the CDC.",
      "url": "https://www.fastcompany.com/91540866/brain-eating-amoeba-found-in-u-s-national-parks-risk-safety-infection-symptoms-what-to-know",
      "image_url": "https://images.fastcompany.com/image/upload/w_1280,q_auto,f_auto,fl_lossy/f_webp,q_auto,c_fit/wp-cms-2/2026/05/p-1-91540866-Brain-eating-amoeba-found-in-these-two-national-parks.jpg",
      "source_icon": "https://n.bytvi.com/fastcompany.png",
      "source": "Fast Company",
      "published_at": "2026-05-12 18:30:00",
      "language": "english",
      "category": "environment"
    },
    {
      "id": "57b612598991bf0e1c3dc6935d35ec80",
      "title": "Why the race to save these cherished penguins just became more urgent",
      "description": "Researchers found the endangered yellow-eyed penguin is made up of three distinct subspecies, with the mainland lineage at greatest risk.",
      "url": "https://theconversation.com/why-the-race-to-save-these-cherished-penguins-just-became-more-urgent-282579",
      "image_url": "https://images.theconversation.com/files/735222/original/file-20260512-57-poeicm.jpg?ixlib=rb-4.1.0&rect=0%2C417%2C5000%2C2500&q=45&auto=format&w=1356&h=668&fit=crop",
      "source_icon": "https://n.bytvi.com/theconversation.png",
      "source": "The Conversation",
      "published_at": "2026-05-12 18:23:55",
      "language": "english",
      "category": "environment"
    },
    {
      "id": "c4eb2756797801304663ecbb33ecc0c2",
      "title": "Why Georgia ranks as a bad state for animals in recent Smilehub study",
      "description": "Is Georgia a good state for animals? Smilehub ranked the quality of states' animal welfare. What is the best? What is the worst? Based on what?",
      "url": "https://www.yahoo.com/news/articles/why-georgia-ranks-bad-state-182049779.html",
      "image_url": "https://media.zenfs.com/en/savannah-morning-news/b06812750e1189d8b2c00fe8516cf65f",
      "source_icon": "https://n.bytvi.com/yahoo.png",
      "source": "Yahoo! News",
      "published_at": "2026-05-12 18:20:49",
      "language": "english",
      "category": "environment"
    },
    {
      "id": "470556ac13e4e4b1f9559891c459b32a",
      "title": "Is the world ready for a record-breaking El Niño?",
      "description": "Drought and flooding could plague the world into 2027",
      "url": "https://theweek.com/science/el-nino-record-weather-impacts-climate-change",
      "image_url": "https://cdn.mos.cms.futurecdn.net/RNxE9nLfJCfZGiXyH2BLNY-1280-80.jpg",
      "source_icon": "https://n.bytvi.com/theweek.png",
      "source": "The Week",
      "published_at": "2026-05-12 18:08:06",
      "language": "english",
      "category": "environment"
    },
    {
      "id": "ae2aef9d309d61869506e72d283c140d",
      "title": "Some residents allowed home as crews suppress Wickenburg fire",
      "description": "The Jones Fire in Wickenburg remained in is original footprint overnight, but officials warned that high temperatures could generate flareups.",
      "url": "https://www.azcentral.com/story/news/local/arizona-wildfires/2026/05/12/some-residents-back-home-after-jones-fire-hits-wickenburg/90039541007/",
      "image_url": "https://www.gannett-cdn.com/authoring/authoring-images/2026/05/12/PPHX/90045931007-jones-fire-008.jpg?auto=webp&crop=3899,2193,x0,y203&format=pjpg&width=1200",
      "source_icon": "https://n.bytvi.com/azcentral.png",
      "source": "The Arizona Republic",
      "published_at": "2026-05-12 18:07:44",
      "language": "english",
      "category": "environment"
    }
  ]
}